Metadata-Version: 2.1
Name: easiest-sort
Version: 0.0.2
Summary: Python module for easiest and fast sort
Home-page: https://github.com/eliastikus/Python
Author: Eliastikus
Author-email: eliastikus@gmail.com
Project-URL: GitHub, https://github.com/eliastikus
Keywords: easiest sort
Classifier: Programming Language :: Python :: 3.13
Classifier: License :: OSI Approved :: Apache Software License
Classifier: Operating System :: OS Independent
